awesome/__init__.py
awesome/__main__.py
awesome/cache.py
awesome/parser_loader.py
awesome/tui.py
awesome/parsers/__init__.py
awesome/parsers/android.py
awesome/parsers/awesome.py
awesome/parsers/elixir.py
awesome/parsers/erlang.py
awesome/parsers/go.py
awesome/parsers/ios.py
awesome/parsers/java.py
awesome/parsers/javascript.py
awesome/parsers/nodejs.py
awesome/parsers/php.py
awesome/parsers/python.py
awesome/parsers/ruby.py
awesome/parsers/rust.py
awesome/parsers/scala.py
awesome/parsers/shell.py
awesome/parsers/swift.py
awesome/parsers/vue.py
awesome_finder-1.2.3.dist-info/LICENSE
awesome_finder-1.2.3.dist-info/METADATA
awesome_finder-1.2.3.dist-info/WHEEL
awesome_finder-1.2.3.dist-info/entry_points.txt
awesome_finder-1.2.3.dist-info/top_level.txt
awesome_finder-1.2.3.dist-info/RECORD
