Metadata-Version: 2.1
Name: awesome-finder
Version: 1.2.3
Summary: A TUI based awesome curated list finder
Home-page: https://github.com/mingrammer/awesome-finder
Author: mingrammer
Author-email: mingrammer@gmail.com
License: MIT
Keywords: awesome finder curses tui
Platform: UNKNOWN
Classifier: License :: OSI Approved :: MIT License
Classifier: Programming Language :: Python
Classifier: Programming Language :: Python :: 3
Classifier: Programming Language :: Python :: 3.3
Classifier: Programming Language :: Python :: 3.4
Classifier: Programming Language :: Python :: 3.5
Classifier: Programming Language :: Python :: 3.6
Classifier: Programming Language :: Python :: 3.7
Classifier: Programming Language :: Python :: 3.8
Classifier: Programming Language :: Python :: Implementation :: CPython
Classifier: Programming Language :: Python :: Implementation :: PyPy
Classifier: Topic :: Terminals
Requires-Python: >=3
Requires-Dist: requests (==2.18.4)
